{"chunk_definitions":[{"row":74,"row_count":1,"visible":true,"expansion_state":0,"options":{"warning":null,"engine":"r","label":"unnamed-chunk-1"},"document_id":"B74C4843","chunk_id":"cs91bv7xb45ng","chunk_label":"unnamed-chunk-1"},{"row":91,"row_count":1,"visible":true,"expansion_state":0,"options":{"engine":"r","label":"unnamed-chunk-2"},"document_id":"B74C4843","chunk_id":"cef4bjcvhijpl","chunk_label":"unnamed-chunk-2"},{"row":255,"row_count":1,"visible":true,"expansion_state":0,"options":{"engine":"r","label":"unnamed-chunk-3"},"document_id":"B74C4843","chunk_id":"cub6ifnbrkxs3","chunk_label":"unnamed-chunk-3"},{"row":284,"row_count":1,"visible":true,"expansion_state":0,"options":{"engine":"r","label":"unnamed-chunk-4"},"document_id":"B74C4843","chunk_id":"cic4wcx3pknr3","chunk_label":"unnamed-chunk-4"},{"row":345,"row_count":1,"visible":true,"expansion_state":0,"options":{"engine":"r","echo":false,"label":"unnamed-chunk-5"},"document_id":"B74C4843","chunk_id":"c3c33ysuhfijl","chunk_label":"unnamed-chunk-5"},{"row":408,"row_count":1,"visible":true,"expansion_state":0,"options":{"engine":"r","label":"unnamed-chunk-6"},"document_id":"B74C4843","chunk_id":"cjb6nbo8siswk","chunk_label":"unnamed-chunk-6"},{"row":414,"row_count":1,"visible":true,"expansion_state":0,"options":{"engine":"r","label":"unnamed-chunk-7"},"document_id":"B74C4843","chunk_id":"coie1m99nelfs","chunk_label":"unnamed-chunk-7"},{"row":425,"row_count":1,"visible":true,"expansion_state":0,"options":{"warning":false,"engine":"r","label":"unnamed-chunk-8"},"document_id":"B74C4843","chunk_id":"cn71xtmbpwjcr","chunk_label":"unnamed-chunk-8"},{"row":441,"row_count":1,"visible":true,"expansion_state":0,"options":{"engine":"r","label":"unnamed-chunk-9"},"document_id":"B74C4843","chunk_id":"crf53q617pbmx","chunk_label":"unnamed-chunk-9"},{"row":466,"row_count":1,"visible":true,"expansion_state":0,"options":{"warning":false,"message":false,"engine":"r","label":"unnamed-chunk-22"},"document_id":"5C82DB12","chunk_id":"crbok7tvmhcgj","chunk_label":"unnamed-chunk-10"},{"row":75,"row_count":1,"visible":true,"expansion_state":0,"options":{"warning":null,"engine":"r","label":"unnamed-chunk-1"},"document_id":"B74C4843","chunk_id":"cs91bv7xb45ng","chunk_label":"unnamed-chunk-1"},{"row":92,"row_count":1,"visible":true,"expansion_state":0,"options":{"engine":"r","label":"unnamed-chunk-2"},"document_id":"B74C4843","chunk_id":"cef4bjcvhijpl","chunk_label":"unnamed-chunk-2"},{"row":256,"row_count":1,"visible":true,"expansion_state":0,"options":{"engine":"r","label":"unnamed-chunk-3"},"document_id":"B74C4843","chunk_id":"cub6ifnbrkxs3","chunk_label":"unnamed-chunk-3"},{"row":285,"row_count":1,"visible":true,"expansion_state":0,"options":{"engine":"r","label":"unnamed-chunk-4"},"document_id":"B74C4843","chunk_id":"cic4wcx3pknr3","chunk_label":"unnamed-chunk-4"},{"row":346,"row_count":1,"visible":true,"expansion_state":0,"options":{"engine":"r","echo":false,"label":"unnamed-chunk-5"},"document_id":"B74C4843","chunk_id":"c3c33ysuhfijl","chunk_label":"unnamed-chunk-5"},{"row":409,"row_count":1,"visible":true,"expansion_state":0,"options":{"engine":"r","label":"unnamed-chunk-6"},"document_id":"B74C4843","chunk_id":"cjb6nbo8siswk","chunk_label":"unnamed-chunk-6"},{"row":415,"row_count":1,"visible":true,"expansion_state":0,"options":{"engine":"r","label":"unnamed-chunk-7"},"document_id":"B74C4843","chunk_id":"coie1m99nelfs","chunk_label":"unnamed-chunk-7"},{"row":426,"row_count":1,"visible":true,"expansion_state":0,"options":{"warning":false,"engine":"r","label":"unnamed-chunk-8"},"document_id":"B74C4843","chunk_id":"cn71xtmbpwjcr","chunk_label":"unnamed-chunk-8"},{"row":442,"row_count":1,"visible":true,"expansion_state":0,"options":{"engine":"r","label":"unnamed-chunk-9"},"document_id":"B74C4843","chunk_id":"crf53q617pbmx","chunk_label":"unnamed-chunk-9"},{"row":467,"row_count":1,"visible":true,"expansion_state":0,"options":{"warning":false,"message":false,"engine":"r","label":"unnamed-chunk-22"},"document_id":"5C82DB12","chunk_id":"crbok7tvmhcgj","chunk_label":"unnamed-chunk-10"},{"row":75,"row_count":1,"visible":true,"expansion_state":0,"options":{"warning":null,"engine":"r","label":"unnamed-chunk-1"},"document_id":"B74C4843","chunk_id":"cs91bv7xb45ng","chunk_label":"unnamed-chunk-1"},{"row":92,"row_count":1,"visible":true,"expansion_state":0,"options":{"engine":"r","label":"unnamed-chunk-2"},"document_id":"B74C4843","chunk_id":"cef4bjcvhijpl","chunk_label":"unnamed-chunk-2"},{"row":256,"row_count":1,"visible":true,"expansion_state":0,"options":{"engine":"r","label":"unnamed-chunk-3"},"document_id":"B74C4843","chunk_id":"cub6ifnbrkxs3","chunk_label":"unnamed-chunk-3"},{"row":285,"row_count":1,"visible":true,"expansion_state":0,"options":{"engine":"r","label":"unnamed-chunk-4"},"document_id":"B74C4843","chunk_id":"cic4wcx3pknr3","chunk_label":"unnamed-chunk-4"},{"row":346,"row_count":1,"visible":true,"expansion_state":0,"options":{"engine":"r","echo":false,"label":"unnamed-chunk-5"},"document_id":"B74C4843","chunk_id":"c3c33ysuhfijl","chunk_label":"unnamed-chunk-5"},{"row":409,"row_count":1,"visible":true,"expansion_state":0,"options":{"engine":"r","label":"unnamed-chunk-6"},"document_id":"B74C4843","chunk_id":"cjb6nbo8siswk","chunk_label":"unnamed-chunk-6"},{"row":415,"row_count":1,"visible":true,"expansion_state":0,"options":{"engine":"r","label":"unnamed-chunk-7"},"document_id":"B74C4843","chunk_id":"coie1m99nelfs","chunk_label":"unnamed-chunk-7"},{"row":426,"row_count":1,"visible":true,"expansion_state":0,"options":{"warning":false,"engine":"r","label":"unnamed-chunk-8"},"document_id":"B74C4843","chunk_id":"cn71xtmbpwjcr","chunk_label":"unnamed-chunk-8"},{"row":442,"row_count":1,"visible":true,"expansion_state":0,"options":{"engine":"r","label":"unnamed-chunk-9"},"document_id":"B74C4843","chunk_id":"crf53q617pbmx","chunk_label":"unnamed-chunk-9"},{"row":467,"row_count":1,"visible":true,"expansion_state":0,"options":{"warning":false,"message":false,"engine":"r","label":"unnamed-chunk-22"},"document_id":"5C82DB12","chunk_id":"crbok7tvmhcgj","chunk_label":"unnamed-chunk-10"}],"doc_write_time":1660806112,"chunk_rendered_width":667}